webscrapeanything/__init__.py
webscrapeanything/main.py
webscrapeanything-0.1.4.dist-info/LICENSE
webscrapeanything-0.1.4.dist-info/METADATA
webscrapeanything-0.1.4.dist-info/WHEEL
webscrapeanything-0.1.4.dist-info/entry_points.txt
webscrapeanything-0.1.4.dist-info/top_level.txt
webscrapeanything-0.1.4.dist-info/RECORD
