Metadata-Version: 2.1
Name: webscrapeanything
Version: 0.1.4
Summary: A package for web scraping and automation with AWS deployment capabilities
Home-page: https://github.com/yourusername/webscrapeanything
Author: Your Name
Author-email: your.email@example.com
Classifier: Programming Language :: Python :: 3
Classifier: License :: OSI Approved :: MIT License
Classifier: Operating System :: OS Independent
Requires-Python: >=3.6
License-File: LICENSE
Requires-Dist: selenium
Requires-Dist: boto3
Requires-Dist: gspread
Requires-Dist: oauth2client
Requires-Dist: pymysql
